objex/__init__.py
objex/__main__.py
objex/dbutils.py
objex/explorer.py
objex/exporter.py
objex/schema.py
objex-0.15.dev0.dist-info/DESCRIPTION.rst
objex-0.15.dev0.dist-info/METADATA
objex-0.15.dev0.dist-info/RECORD
objex-0.15.dev0.dist-info/WHEEL
objex-0.15.dev0.dist-info/metadata.json
objex-0.15.dev0.dist-info/top_level.txt
